Metadata-Version: 2.1
Name: datamoire
Version: 0.0.0
Summary: Python library for data processing
Home-page: https://github.com/lsdrfrx/datamoire
Author: Christian Guetnga
Author-email: lsdrfrx@gmail.com
License-File: LICENSE
